axonbot/__init__.py
axonbot/axonbot.py
axonbot/axonwebsocket.py
axonbot-0.3.3.dist-info/LICENSE
axonbot-0.3.3.dist-info/METADATA
axonbot-0.3.3.dist-info/WHEEL
axonbot-0.3.3.dist-info/top_level.txt
axonbot-0.3.3.dist-info/RECORD
