Metadata-Version: 2.1
Name: axonbot
Version: 0.3.3
Summary: Axon is an artificially intelligent agent that trades bitcoin based on daily forecasts.
Home-page: https://github.com/axonintel/axon
Author: Shehadi Dayekh
Author-email: shehadi@axonintellex.com
License: MIT
Download-URL: https://github.com/axonintel/axon/archive/refs/heads/main.zip
Keywords: gdax,gdax-api,orderbook,trade,bitcoin,BTC,client,api,wrapper,exchange,crypto,currency,trading,trading-api,coinbase,AI,ML,pro,prime,coinbasepro
Platform: UNKNOWN
Classifier: Development Status :: 5 - Production/Stable
Classifier: Intended Audience :: Developers
Classifier: Intended Audience :: Financial and Insurance Industry
Classifier: Intended Audience :: Information Technology
Classifier: Topic :: Software Development :: Libraries :: Python Modules
Classifier: License :: OSI Approved :: MIT License
Classifier: Programming Language :: Python :: 3.9
Requires-Python: >=3, <3.9
Requires-Dist: cbpro (>=1.1.4)
